mdss/__init__.py
mdss/dissimilarity.py
mdss/geometrical_property.py
mdss/graph.py
mdss/log_setup.py
mdss/parser.py
mdss/pca_property.py
mdss/property.py
mdss/protein_data.py
mdss/run.py
mdss/sampler.py
mdss/scenarios/__init__.py
mdss/scenarios/scenario_1.ipynb
mdss/scenarios/scenario_1.py
mdss/scenarios/scenario_2.ipynb
mdss/scenarios/scenario_2.py
mdss/scenarios/scenario_3.ipynb
mdss/scenarios/scenario_3.py
mdss/utilities.py
mdsubsampler-0.0.8.dist-info/LICENSE
mdsubsampler-0.0.8.dist-info/METADATA
mdsubsampler-0.0.8.dist-info/WHEEL
mdsubsampler-0.0.8.dist-info/entry_points.txt
mdsubsampler-0.0.8.dist-info/RECORD
