Metadata-Version: 2.1
Name: mdsubsampler
Version: 0.0.8
Summary: 
License: GPL-3.0-only
Author: Namir Oues
Author-email: namir.oues@brunel.ac.uk
Requires-Python: >=3.9,<4.0
Classifier: License :: OSI Approved :: GNU General Public License v3 (GPLv3)
Classifier: Programming Language :: Python :: 3
Classifier: Programming Language :: Python :: 3.9
Classifier: Programming Language :: Python :: 3.10
Classifier: Programming Language :: Python :: 3.11
Classifier: Programming Language :: Python :: 3.12
Requires-Dist: MDAnalysis (>=2.1.0,<3.0.0)
Requires-Dist: dictances (==1.5.3)
Requires-Dist: matplotlib (>=3.6.2,<4.0.0)
Requires-Dist: numpy (>=1.23.5,<2.0.0)
Requires-Dist: pandas (>=1.5.2,<2.0.0)
Requires-Dist: psutil (>=5.9.4,<6.0.0)
Requires-Dist: pytest (>=7.2.0,<8.0.0)
Requires-Dist: pytest-mock (>=3.10.0,<4.0.0)
Requires-Dist: scikit-learn (>=1.2.2,<2.0.0)
Requires-Dist: setuptools (>=69.0.3,<70.0.0)
